fastscape/__init__.py
fastscape/models/__init__.py
fastscape/models/_models.py
fastscape/processes/__init__.py
fastscape/processes/boundary.py
fastscape/processes/channel.py
fastscape/processes/context.py
fastscape/processes/erosion.py
fastscape/processes/flow.py
fastscape/processes/grid.py
fastscape/processes/hillslope.py
fastscape/processes/initial.py
fastscape/processes/isostasy.py
fastscape/processes/main.py
fastscape/processes/marine.py
fastscape/processes/tectonics.py
fastscape/tests/__init__.py
fastscape/tests/fixtures.py
fastscape/tests/test_processes_boundary.py
fastscape/tests/test_processes_context.py
fastscape/tests/test_processes_grid.py
fastscape/tests/test_processes_initial.py
fastscape/tests/test_processes_main.py
fastscape/tests/test_processes_tectonics.py
fastscape-0.1.0.dist-info/LICENSE
fastscape-0.1.0.dist-info/METADATA
fastscape-0.1.0.dist-info/WHEEL
fastscape-0.1.0.dist-info/top_level.txt
fastscape-0.1.0.dist-info/RECORD
