Metadata-Version: 2.1
Name: fastscape
Version: 0.1.0
Summary: A fast, versatile and user-friendly landscape evolution model
Author-email: Benoît Bovy <benbovy@gmail.com>
Maintainer: Fastscape contributors
License: BSD-3-Clause
Project-URL: Documentation, https://fastscape.readthedocs.io
Project-URL: Repository, https://github.com/fastscape-lem/fastscape
Keywords: simulation,toolkit,modeling,landscape,geomorphology
Classifier: Intended Audience :: Science/Research
Classifier: License :: OSI Approved :: BSD License
Classifier: Programming Language :: Python :: 3
Requires-Python: >=3.9
License-File: LICENSE
Requires-Dist: xarray-simlab >=0.5.0
Requires-Dist: numba
Provides-Extra: dev
Requires-Dist: pytest ; extra == 'dev'
